batch_football_data-0.0.9.dist-info/licenses/LICENSE
football_data/__init__.py
football_data/models.py
football_data/repositories.py
batch_football_data-0.0.9.dist-info/METADATA
batch_football_data-0.0.9.dist-info/WHEEL
batch_football_data-0.0.9.dist-info/top_level.txt
batch_football_data-0.0.9.dist-info/RECORD
