Metadata-Version: 2.4
Name: batch-football-data
Version: 0.0.9
Summary: Data Access Library for interacting with the FB Stats Postgres Database.
Author: runstache
Project-URL: Homepage, https://github.com/runstache/py-football-data
Project-URL: Bug Tracker, https://github.com/runstache/py-football-data/issues
Classifier: Programming Language :: Python :: 3
Classifier: License :: OSI Approved :: MIT License
Classifier: Operating System :: OS Independent
Requires-Python: >=3.12
License-File: LICENSE
Requires-Dist: sqlalchemy>=2.0.38
Dynamic: license-file
